smwsync/__init__.py
smwsync/mapping.py
smwsync/synccmd.py
smwsync/version.py
pysmwsync-0.1.2.dist-info/METADATA
pysmwsync-0.1.2.dist-info/WHEEL
pysmwsync-0.1.2.dist-info/entry_points.txt
pysmwsync-0.1.2.dist-info/licenses/LICENSE
pysmwsync-0.1.2.dist-info/RECORD
